redmost/__init__.py
redmost/_version.py
redmost/gui.py
redmost/lines.py
redmost/loaders.py
redmost/py.typed
redmost/qt_compat.py
redmost/utils.py
redmost/backends/__init__.py
redmost/backends/rrock.py
redmost/ui/control_mapping_dialog.ui
redmost/ui/main_window.ui
redmost/ui/redmost.png
redmost/ui/settings_dialog.ui
redmost/ui/icons/feather/book.svg
redmost/ui/icons/feather/camera.svg
redmost/ui/icons/feather/check-square.svg
redmost/ui/icons/feather/chevrons-left.svg
redmost/ui/icons/feather/chevrons-right.svg
redmost/ui/icons/feather/delete.svg
redmost/ui/icons/feather/file-minus.svg
redmost/ui/icons/feather/file-plus.svg
redmost/ui/icons/feather/file.svg
redmost/ui/icons/feather/folder.svg
redmost/ui/icons/feather/info.svg
redmost/ui/icons/feather/log-out.svg
redmost/ui/icons/feather/maximize.svg
redmost/ui/icons/feather/minus-square.svg
redmost/ui/icons/feather/play.svg
redmost/ui/icons/feather/plus-square.svg
redmost/ui/icons/feather/plus.svg
redmost/ui/icons/feather/save.svg
redmost/ui/icons/feather/save_as.svg
redmost/ui/icons/feather/settings.svg
redmost/ui/icons/feather/share.svg
redmost/ui/icons/feather/sliders.svg
redmost/ui/icons/feather/table.svg
redmost/ui/icons/feather/x-octagon.svg
redmost/ui/icons/feather/zoom-in.svg
redmost/ui/icons/feather/zoom-out.svg
redmost/ui/icons/feather-dark/book.svg
redmost/ui/icons/feather-dark/camera.svg
redmost/ui/icons/feather-dark/check-square.svg
redmost/ui/icons/feather-dark/chevrons-left.svg
redmost/ui/icons/feather-dark/chevrons-right.svg
redmost/ui/icons/feather-dark/delete.svg
redmost/ui/icons/feather-dark/file-minus.svg
redmost/ui/icons/feather-dark/file-plus.svg
redmost/ui/icons/feather-dark/file.svg
redmost/ui/icons/feather-dark/folder.svg
redmost/ui/icons/feather-dark/info.svg
redmost/ui/icons/feather-dark/log-out.svg
redmost/ui/icons/feather-dark/maximize.svg
redmost/ui/icons/feather-dark/minus-square.svg
redmost/ui/icons/feather-dark/play.svg
redmost/ui/icons/feather-dark/plus-square.svg
redmost-0.4.7.dist-info/LICENSE
redmost-0.4.7.dist-info/METADATA
redmost-0.4.7.dist-info/WHEEL
redmost-0.4.7.dist-info/entry_points.txt
redmost-0.4.7.dist-info/top_level.txt
redmost-0.4.7.dist-info/RECORD
