Metadata-Version: 2.1
Name: redmost
Version: 0.4.7
Summary: Display spectra and estimate their redshifts.
Author: Maurizio D'Addona
Author-email: mauritiusdadd@gmail.com
Maintainer: Maurizio D'Addona
Maintainer-email: mauritiusdadd@gmail.com
License: BSD 3-Clause License
Project-URL: repository, https://github.com/mauritiusdadd/redmost
Keywords: spectroscopy,FITS,astronomy
Classifier: Development Status :: 3 - Alpha
Classifier: Intended Audience :: Science/Research
Classifier: Topic :: Multimedia :: Graphics :: Graphics Conversion
Classifier: Programming Language :: Python :: 3
Requires-Python: >=3.8
License-File: LICENSE
Requires-Dist: numpy
Requires-Dist: scipy
Requires-Dist: astropy
Requires-Dist: specutils
Provides-Extra: pyqt5
Requires-Dist: PyQt5 ; extra == 'pyqt5'
Requires-Dist: PyQtChart ; extra == 'pyqt5'
Provides-Extra: pyqt6
Requires-Dist: PyQt6 ; extra == 'pyqt6'
Requires-Dist: PyQt6-Charts ; extra == 'pyqt6'
Provides-Extra: pyside6
Requires-Dist: PySide6 ; extra == 'pyside6'
Provides-Extra: redrock
Requires-Dist: redrock ; extra == 'redrock'
Provides-Extra: test
Requires-Dist: pytest ; extra == 'test'
Requires-Dist: pytest-qt ; extra == 'test'
Requires-Dist: coverage ; extra == 'test'
